{"_type":"export","__export_format":4,"__export_date":"2021-07-01T00:14:22.084Z","__export_source":"insomnia.desktop.app:v2021.3.0","resources":[{"_id":"req_353fec6dff8c45508a9b00c8109fb85d","parentId":"wrk_8f5c6f256cf04f4588efd044224e1cfb","modified":1625098384775,"created":1625098220637,"url":"https://localhost:5001/api/hotels/2","name":"Put_Hotel","description":"","method":"PUT","body":{"mimeType":"application/json","text":"{   \"hotelID\": \"2\",\n    \"hotelName\": \"Brisadamanha\",\n    \"hotelDescription\": \"l oferece uma das melhores localizações Moderno, contemporâneo e elegante, é perfeito para estadias a dois ou em família.\",\n    \"hotelAssessment\": \"Bom \",\n    \"hotelAddress\": \"Avenida Jose Ramos , 8023 2765-300 Monte Estoril Portugal\",\n    \"hotelConvenience\": \"Fitness Centre, Cabeleireiro, wifi, area de cuidados infatil, garagem, manobrista\"\n  }"},"parameters":[],"headers":[{"name":"Content-Type","value":"application/json","id":"pair_45b5204aba744f3ab0f1cb40eb8449bf"}],"authentication":{},"metaSortKey":-1625098220637,"isPrivate":false,"settingStoreCookies":true,"settingSendCookies":true,"settingDisableRenderRequestBody":false,"settingEncodeUrl":true,"settingRebuildPath":true,"settingFollowRedirects":"global","_type":"request"},{"_id":"wrk_8f5c6f256cf04f4588efd044224e1cfb","parentId":null,"modified":1625087209559,"created":1625087209559,"name":"API-Hotel","description":"","scope":"collection","_type":"workspace"},{"_id":"req_67317666c13f489184777d8c5039da23","parentId":"wrk_8f5c6f256cf04f4588efd044224e1cfb","modified":1625098408782,"created":1625098205342,"url":"https://localhost:5001/api/hotels/1","name":"Delete_Hotel","description":"","method":"DELETE","body":{},"parameters":[],"headers":[],"authentication":{},"metaSortKey":-1625098205342,"isPrivate":false,"settingStoreCookies":true,"settingSendCookies":true,"settingDisableRenderRequestBody":false,"settingEncodeUrl":true,"settingRebuildPath":true,"settingFollowRedirects":"global","_type":"request"},{"_id":"req_fcb6e1fc341e4c818c981be6cb2f579d","parentId":"wrk_8f5c6f256cf04f4588efd044224e1cfb","modified":1625098341700,"created":1625098160651,"url":"https://localhost:5001/api/hotels","name":"Post_Hotel","description":"","method":"POST","body":{"mimeType":"application/json","text":"{   \"hotelID\": \"2\",\n    \"hotelName\": \"Brisadamanha\",\n    \"hotelDescription\": \"l oferece uma das melhores localizações Moderno, contemporâneo e elegante, é perfeito para estadias a dois ou em família.\",\n    \"hotelAssessment\": \"Bom \",\n    \"hotelAddress\": \"Avenida Jose Ramos , 8023 2765-300 Monte Estoril Portugal\",\n    \"hotelConvenience\": \"Bar, Fitness Centre, Cabeleireiro, wifi, area de cuidados infatil, garagem, manobrista\"\n  }"},"parameters":[],"headers":[{"name":"Content-Type","value":"application/json","id":"pair_4248bf66c35c4179835d0db4981dbd17"}],"authentication":{},"metaSortKey":-1625098160651,"isPrivate":false,"settingStoreCookies":true,"settingSendCookies":true,"settingDisableRenderRequestBody":false,"settingEncodeUrl":true,"settingRebuildPath":true,"settingFollowRedirects":"global","_type":"request"},{"_id":"req_99300460eff44c21a9c191a752d0468d","parentId":"wrk_8f5c6f256cf04f4588efd044224e1cfb","modified":1625098185961,"created":1625087511608,"url":"https://localhost:5001/api/hotels","name":"Query_Hotel","description":"","method":"GET","body":{"mimeType":"application/json","text":""},"parameters":[],"headers":[{"name":"Content-Type","value":"application/json","id":"pair_e666e284d2764ad48534ad2f7cd0677e"}],"authentication":{},"metaSortKey":-1625087511608,"isPrivate":false,"settingStoreCookies":true,"settingSendCookies":true,"settingDisableRenderRequestBody":false,"settingEncodeUrl":true,"settingRebuildPath":true,"settingFollowRedirects":"global","_type":"request"},{"_id":"env_e01817a64489f4a772fd61719d2da1e695072257","parentId":"wrk_8f5c6f256cf04f4588efd044224e1cfb","modified":1625087209811,"created":1625087209811,"name":"Base Environment","data":{},"dataPropertyOrder":null,"color":null,"isPrivate":false,"metaSortKey":1625087209811,"_type":"environment"},{"_id":"jar_e01817a64489f4a772fd61719d2da1e695072257","parentId":"wrk_8f5c6f256cf04f4588efd044224e1cfb","modified":1625087209815,"created":1625087209815,"name":"Default Jar","cookies":[],"_type":"cookie_jar"},{"_id":"spc_b070c33f8b0140839150f3bcb3cff128","parentId":"wrk_8f5c6f256cf04f4588efd044224e1cfb","modified":1625087209563,"created":1625087209563,"fileName":"API-Hotel","contents":"","contentType":"yaml","_type":"api_spec"}]}